dlr_sc_quark-1.2.1.dist-info/licenses/LICENSE
quark/__init__.py
quark/constrained_objective.py
quark/constraint_binary.py
quark/embedding.py
quark/hardware_adjacency.py
quark/objective.py
quark/objective_terms.py
quark/poly_binary.py
quark/poly_ising.py
quark/polynomial.py
quark/scip_model.py
quark/solution.py
quark/variable_mapping.py
quark/variables.py
quark/io/__init__.py
quark/io/_constrained_objective.py
quark/io/_constraint_binary.py
quark/io/_embedding.py
quark/io/_hardware_adjacency.py
quark/io/_objective.py
quark/io/_objective_terms.py
quark/io/_poly_binary.py
quark/io/_poly_ising.py
quark/io/_polynomial.py
quark/io/_solution.py
quark/io/_variable_mapping.py
quark/io/add.py
quark/io/hdf5.py
quark/io/hdf5_attributes.py
quark/io/hdf5_datasets.py
quark/io/instance.py
quark/io/poly_utils.py
quark/io/txt.py
quark/testing/__init__.py
quark/testing/example_config.py
quark/testing/example_constrained_objective.py
quark/testing/example_instance.py
quark/testing/example_objective.py
quark/testing/example_objective_terms.py
quark/utils/__init__.py
quark/utils/config.py
quark/utils/logger.py
quark/utils/variables.py
dlr_sc_quark-1.2.1.dist-info/METADATA
dlr_sc_quark-1.2.1.dist-info/WHEEL
dlr_sc_quark-1.2.1.dist-info/top_level.txt
dlr_sc_quark-1.2.1.dist-info/RECORD
