Metadata-Version: 2.4
Name: dlr-sc-quark
Version: 1.2.1
Summary: This is a software package to support the mapping of combinatorial optimization problems to quantum computing interfaces via QUBO and Ising problems.
Home-page: https://gitlab.com/quantum-computing-software/quark/
Author: DLR-SC
Author-email: DLR-SC <qc-software@dlr.de>
License-Expression: Apache-2.0
Project-URL: Homepage, https://gitlab.com/quantum-computing-software/quark/
Project-URL: Documentation, https://quantum-computing-software.gitlab.io/quark/
Keywords: Combinatorial Optimization,QUBO,Ising Problem,Quantum Computing,Quantum Annealing
Classifier: Programming Language :: Python :: 3
Classifier: Operating System :: OS Independent
Requires-Python: >=3.11
License-File: LICENSE
Requires-Dist: h5py
Requires-Dist: pyscipopt
Requires-Dist: numpy
Requires-Dist: pytest
Requires-Dist: networkx
Requires-Dist: bidict
Requires-Dist: matplotlib
Requires-Dist: jupyter
Dynamic: author
Dynamic: home-page
Dynamic: license-file
Dynamic: requires-python
